psdtojpg.py
psdtojpg-0.1.0.dist-info/DESCRIPTION.rst
psdtojpg-0.1.0.dist-info/entry_points.txt
psdtojpg-0.1.0.dist-info/METADATA
psdtojpg-0.1.0.dist-info/metadata.json
psdtojpg-0.1.0.dist-info/RECORD
psdtojpg-0.1.0.dist-info/top_level.txt
psdtojpg-0.1.0.dist-info/WHEEL
