Metadata-Version: 2.0
Name: psdtojpg
Version: 0.1.0
Summary: Convert one or more PSD files to JPG format. Thumbnail and optimize them, or don't.
Home-page: https://github.com/mplewis/psdtojpg
Author: Matthew Lewis
Author-email: matt@mplewis.com
License: MIT
Platform: UNKNOWN
Classifier: Development Status :: 4 - Beta
Classifier: Natural Language :: English
Classifier: License :: OSI Approved :: MIT License
Classifier: Operating System :: OS Independent
Classifier: Programming Language :: Python
Classifier: Programming Language :: Python :: 3
Classifier: Programming Language :: Python :: 3.4
Classifier: Topic :: Multimedia :: Graphics :: Graphics Conversion
Requires-Dist: Pillow (>=2.5.1,<3.0.0)
Requires-Dist: psd-tools (>=0.10,<1.0)
